setup.cfg
setup.py
bin/mtg
mtg.egg-info/PKG-INFO
mtg.egg-info/SOURCES.txt
mtg.egg-info/dependency_links.txt
mtg.egg-info/requires.txt
mtg.egg-info/top_level.txt
mtglib/__init__.py
mtglib/card_extractor.py
mtglib/card_renderer.py
mtglib/colors.py
mtglib/constants.py
mtglib/functions.py
mtglib/gatherer_request.py