Metadata-Version: 1.1
Name: mtg
Version: 1.6.1
Summary: Console-based access to the Gatherer Magic Card Database.
Home-page: https://github.com/chigby/mtg
Author: Cameron Higby-Naquin
Author-email: cameron.higbynaquin@gmail.com
License: MIT
Keywords: mtg,magic,gatherer
Platform: UNKNOWN
Classifier: Development Status :: 5 - Production/Stable
Classifier: Environment :: Console
Classifier: Intended Audience :: End Users/Desktop
Classifier: License :: OSI Approved :: MIT License
Classifier: Natural Language :: English
Classifier: Operating System :: OS Independent
Classifier: Programming Language :: Python :: 2.6
Classifier: Programming Language :: Python :: 2.7
Classifier: Programming Language :: Python :: 3
Classifier: Programming Language :: Python :: 3.3
Classifier: Programming Language :: Python :: 3.4
Classifier: Topic :: Utilities
Classifier: Topic :: Internet :: WWW/HTTP
Classifier: Topic :: Internet :: WWW/HTTP :: Indexing/Search
Classifier: Topic :: Games/Entertainment
